cas_tg/__init__.py
cas_tg/__main__.py
cas_tg-1.0.1.dist-info/LICENSE
cas_tg-1.0.1.dist-info/METADATA
cas_tg-1.0.1.dist-info/WHEEL
cas_tg-1.0.1.dist-info/top_level.txt
cas_tg-1.0.1.dist-info/RECORD
