Metadata-Version: 2.1
Name: cas_tg
Version: 1.0.1
Summary: Checking if user banned by CAS (Combot Anti-Spam System)
Home-page: https://wispace.ru/
Author: wispace
Author-email: wiforumit@gmail.com
Classifier: Programming Language :: Python :: 3.10
Classifier: License :: OSI Approved :: MIT License
Classifier: Operating System :: OS Independent
Requires-Python: >=3.6
License-File: LICENSE
